debacl/__init__.py
debacl/level_set_tree.py
debacl/utils.py
debacl/test/__init__.py
debacl/test/test_lst.py
debacl/test/test_utils.py
debacl-1.1.dist-info/DESCRIPTION.rst
debacl-1.1.dist-info/METADATA
debacl-1.1.dist-info/RECORD
debacl-1.1.dist-info/WHEEL
debacl-1.1.dist-info/metadata.json
debacl-1.1.dist-info/top_level.txt
