Metadata-Version: 2.0
Name: debacl
Version: 1.1
Summary: DEnsity-BAsed CLustering
Home-page: https://github.com/CoAxLab/DeBaCl
Author: Brian Kent
Author-email: bpkent@gmail.com
License: BSD
Platform: UNKNOWN
Classifier: License :: OSI Approved :: BSD License
Classifier: Programming Language :: Python :: 2
Classifier: Programming Language :: Python :: 2.7
Classifier: Programming Language :: Python :: 2 :: Only
Classifier: Topic :: Scientific/Engineering
Classifier: Topic :: Scientific/Engineering :: Mathematics
Classifier: Topic :: Scientific/Engineering :: Visualization
Requires-Dist: networkx
Requires-Dist: prettytable
